ml_metrics/__init__.py
ml_metrics/aggregates.py
ml_metrics/chainable.py
ml_metrics/distributed.py
ml_metrics/ml_metrics.py
ml_metrics/pipeline.py
ml_metrics/signals.py
ml_metrics/types.py
ml_metrics/_src/__init__.py
ml_metrics/_src/base_types.py
ml_metrics/_src/aggregates/__init__.py
ml_metrics/_src/aggregates/base.py
ml_metrics/_src/aggregates/base_test.py
ml_metrics/_src/aggregates/classification.py
ml_metrics/_src/aggregates/classification_test.py
ml_metrics/_src/aggregates/keras_metric_wrapper.py
ml_metrics/_src/aggregates/keras_metric_wrapper_test.py
ml_metrics/_src/aggregates/retrieval.py
ml_metrics/_src/aggregates/retrieval_test.py
ml_metrics/_src/aggregates/rolling_stats.py
ml_metrics/_src/aggregates/rolling_stats_test.py
ml_metrics/_src/aggregates/test_utils.py
ml_metrics/_src/aggregates/text.py
ml_metrics/_src/aggregates/text_test.py
ml_metrics/_src/aggregates/types.py
ml_metrics/_src/aggregates/utils.py
ml_metrics/_src/chainables/__init__.py
ml_metrics/_src/chainables/courier_server.py
ml_metrics/_src/chainables/courier_server_test.py
ml_metrics/_src/chainables/courier_worker.py
ml_metrics/_src/chainables/courier_worker_test.py
ml_metrics/_src/chainables/lazy_fns.py
ml_metrics/_src/chainables/lazy_fns_test.py
ml_metrics/_src/chainables/orchestrate.py
ml_metrics/_src/chainables/orchestrate_test.py
ml_metrics/_src/chainables/transform.py
ml_metrics/_src/chainables/transform_test.py
ml_metrics/_src/chainables/tree.py
ml_metrics/_src/chainables/tree_fns.py
ml_metrics/_src/chainables/tree_fns_test.py
ml_metrics/_src/chainables/tree_test.py
ml_metrics/_src/metrics/__init__.py
ml_metrics/_src/metrics/classification.py
ml_metrics/_src/metrics/classification_test.py
ml_metrics/_src/metrics/retrieval.py
ml_metrics/_src/metrics/retrieval_test.py
ml_metrics/_src/metrics/rolling_stats.py
ml_metrics/_src/metrics/rolling_stats_test.py
ml_metrics/_src/metrics/text.py
ml_metrics/_src/metrics/text_test.py
ml_metrics/_src/metrics/utils.py
py_ml_metrics-0.0.2.dist-info/LICENSE
py_ml_metrics-0.0.2.dist-info/METADATA
py_ml_metrics-0.0.2.dist-info/WHEEL
py_ml_metrics-0.0.2.dist-info/top_level.txt
py_ml_metrics-0.0.2.dist-info/RECORD
