Metadata-Version: 2.1
Name: py-ml-metrics
Version: 0.0.2
Summary: ML-metrics: A library that provides performant and distributed friendly ML metrics implementations.
Author-email: ML metrics team <ml-metrics-dev@google.com>
License:                                  Apache License
Project-URL: homepage, https://github.com/google/ml-metrics
Classifier: Programming Language :: Python :: 3
Classifier: License :: OSI Approved :: Apache Software License
Classifier: Operating System :: POSIX :: Linux
Requires-Python: >=3.11
License-File: LICENSE
Requires-Dist: absl-py
Requires-Dist: cloudpickle
Requires-Dist: immutabledict
Requires-Dist: numpy
Requires-Dist: more-itertools
Provides-Extra: courier
Requires-Dist: dm-launchpad; extra == "courier"
Provides-Extra: signals
Requires-Dist: pillow; extra == "signals"
Provides-Extra: full
Requires-Dist: dm-launchpad; extra == "full"
Requires-Dist: pillow; extra == "full"
